drsip/Cn_symm_criterion.py
drsip/__init__.py
drsip/dist_restraints_filter.py
drsip/save_load.py
drsip/struct_clustering.py
drsip/tilt_angle_criterion.py
drsip-0.28.data/scripts/drsip
drsip-0.28.dist-info/METADATA
drsip-0.28.dist-info/RECORD
drsip-0.28.dist-info/WHEEL
drsip-0.28.dist-info/top_level.txt
