Metadata-Version: 2.1
Name: drsip
Version: 0.28
Summary: DRSIP docking package
Home-page: https://github.com/capslockwizard/drsip/
Author: Justin Chan
Author-email: capslockwizard@gmail.com
License: UNKNOWN
Platform: UNKNOWN
Classifier: Environment :: Console
Classifier: Environment :: Plugins
Classifier: Intended Audience :: Science/Research
Classifier: Topic :: Scientific/Engineering :: Bio-Informatics
Classifier: Programming Language :: Python :: 2.7
Classifier: License :: OSI Approved :: MIT License
Classifier: Operating System :: POSIX :: Linux
Classifier: Operating System :: MacOS
Classifier: Development Status :: 5 - Production/Stable
Requires-Dist: zdock-parser
Requires-Dist: numba
Requires-Dist: numpy
Requires-Dist: scipy
Requires-Dist: pandas
Requires-Dist: u-msgpack-python
Requires-Dist: MDAnalysis
Requires-Dist: biopython
Requires-Dist: drsip-common
Requires-Dist: docking-eval
